worldgames/CurrencyRouletteGame.py
worldgames/GeneralGame.py
worldgames/GuessGame.py
worldgames/Live.py
worldgames/MainGame.py
worldgames/MemoryGame.py
worldgames/__init__.py
worldgames/main.py
worldgames-0.0.1.dist-info/METADATA
worldgames-0.0.1.dist-info/WHEEL
worldgames-0.0.1.dist-info/top_level.txt
worldgames-0.0.1.dist-info/RECORD
