Metadata-Version: 2.1
Name: worldgames
Version: 0.0.1
Summary: fun games
Author: kaylan kreizer
License: UNKNOWN
Platform: UNKNOWN
